{"cameraMode":{"drawMode":0,"name":"Shaded","section":"Shading Mode"},"sceneLighting":true,"audioPlay":false,"sceneViewState":{"m_AlwaysRefresh":false,"showFog":true,"showSkybox":true,"showFlares":true,"showImageEffects":true,"showParticleSystems":true,"showVisualEffectGraphs":true,"m_FxEnabled":true},"in2DMode":false,"pivot":{"x":3.150205373764038,"y":-0.20198871195316316,"z":5.795255184173584},"rotation":{"x":-0.1579667329788208,"y":0.1612541377544403,"z":-0.026157081127166749,"w":-0.9738379716873169},"size":10.0,"orthographic":false}